table1/__init__.py
table1-1.5.1.dist-info/licenses/LICENSE
table1-1.5.1.dist-info/METADATA
table1-1.5.1.dist-info/WHEEL
table1-1.5.1.dist-info/top_level.txt
table1-1.5.1.dist-info/RECORD
