Metadata-Version: 2.4
Name: table1
Version: 1.5.1
Summary: VitalDB Python Libray
Author-email: VitalLab <vital@snu.ac.kr>
License-Expression: MIT
Project-URL: homepage, https://github.com/vitaldb/table1
Requires-Python: >=3.0
License-File: LICENSE
Requires-Dist: numpy
Requires-Dist: pandas
Requires-Dist: rpy2
Requires-Dist: scipy
Dynamic: license-file
